arthaLM/__init__.py
arthaLM/pipeline.py
arthalm-0.1.0.dist-info/METADATA
arthalm-0.1.0.dist-info/WHEEL
arthalm-0.1.0.dist-info/top_level.txt
arthalm-0.1.0.dist-info/RECORD
