Metadata-Version: 2.4
Name: arthaLM
Version: 0.1.0
Summary: Plug-and-play pipeline for Artha LLM
Home-page: https://github.com/vyomie/artha
Author: Vyom N. Patel
Classifier: Programming Language :: Python :: 3
Classifier: License :: OSI Approved :: MIT License
Classifier: Operating System :: OS Independent
Requires-Python: >=3.7
Requires-Dist: torch
Requires-Dist: transformers
Requires-Dist: tqdm
Dynamic: author
Dynamic: classifier
Dynamic: description
Dynamic: description-content-type
Dynamic: home-page
Dynamic: requires-dist
Dynamic: requires-python
Dynamic: summary
